.hgignore
LICENSE
setup.py
PyLua.egg-info/PKG-INFO
PyLua.egg-info/SOURCES.txt
PyLua.egg-info/dependency_links.txt
PyLua.egg-info/requires.txt
PyLua.egg-info/top_level.txt
cffi/build_lua.py
lua/__init__.py
lua/lua.py
lua/lua_values.py
lua/lua_wrap.py
test/__init__.py
test/data/21443387.lua
test/lua/__init__.py
test/lua/_lua.py
test/lua/lua.py
test/lua/lua_values.py
test/lua/lua_wrap.py