Metadata-Version: 1.1
Name: PyLua
Version: 0.1.1
Summary: A cffi based lua package.
Home-page: http://hg.crazycasta.net/PyLua/
Author: Alex Orange
Author-email: crazycasta@gmail.com
License: AGPLv3
Platform: UNKNOWN
Classifier: Development Status :: 2 - Pre-Alpha
Classifier: Intended Audience :: Developers
Classifier: License :: OSI Approved :: GNU Affero General Public License v3
Classifier: Programming Language :: Other Scripting Engines
Classifier: Programming Language :: Python :: 2.7
Classifier: Programming Language :: Python :: Implementation :: CPython
Classifier: Programming Language :: Python :: Implementation :: PyPy
Classifier: Topic :: Software Development :: Interpreters
